docker_custodian/__about__.py
docker_custodian/__init__.py
docker_custodian/args.py
docker_custodian/docker_autostop.py
docker_custodian/docker_gc.py
docker_custodian-0.7.4.dist-info/LICENSE
docker_custodian-0.7.4.dist-info/METADATA
docker_custodian-0.7.4.dist-info/WHEEL
docker_custodian-0.7.4.dist-info/entry_points.txt
docker_custodian-0.7.4.dist-info/top_level.txt
docker_custodian-0.7.4.dist-info/RECORD
